[
  {
    "id": "e1",
    "title": "Auth flow test results",
    "source": "QA Test Suite",
    "sourceType": "metric",
    "strength": "strong",
    "date": "2026-03-30T10:00:00Z",
    "url": null,
    "claimIds": ["cl1"],
    "sourceEntityId": "c8",
    "sourceEntityType": "conversation",
    "description": "95% of auth flow test cases passing. 3 critical edge cases failing around token refresh."
  },
  {
    "id": "e2",
    "title": "Auth provider incident report",
    "source": "StatusPage",
    "sourceType": "external",
    "strength": "moderate",
    "date": "2026-03-29T08:00:00Z",
    "url": "https://status.authprovider.example.com/incidents/2026-03",
    "claimIds": ["cl1", "cl6"],
    "sourceEntityId": null,
    "sourceEntityType": null,
    "description": "Auth provider had 2 outages in March, each lasting 15-30 minutes."
  },
  {
    "id": "e3",
    "title": "Security audit findings",
    "source": "External Audit Report",
    "sourceType": "document",
    "strength": "strong",
    "date": "2026-03-25T17:00:00Z",
    "url": null,
    "claimIds": ["cl1"],
    "sourceEntityId": null,
    "sourceEntityType": null,
    "description": "Penetration test found no critical vulnerabilities in auth flow. Two medium-severity issues flagged."
  },
  {
    "id": "e4",
    "title": "Load test results — 500 users",
    "source": "k6 Load Test",
    "sourceType": "metric",
    "strength": "moderate",
    "date": "2026-03-20T14:00:00Z",
    "url": null,
    "claimIds": ["cl2"],
    "sourceEntityId": "c4",
    "sourceEntityType": "conversation",
    "description": "API handles 500 concurrent users with p95 latency under 200ms. Not yet tested at 1000."
  },
  {
    "id": "e5",
    "title": "Database query performance analysis",
    "source": "Maria Santos",
    "sourceType": "conversation",
    "strength": "weak",
    "date": "2026-04-02T16:00:00Z",
    "url": null,
    "claimIds": ["cl2"],
    "sourceEntityId": "c9",
    "sourceEntityType": "conversation",
    "description": "Verbal estimate that current indexes should support 1000 users. No formal benchmarks."
  },
  {
    "id": "e6",
    "title": "Beta user onboarding survey",
    "source": "Google Forms Survey",
    "sourceType": "metric",
    "strength": "moderate",
    "date": "2026-03-28T11:00:00Z",
    "url": null,
    "claimIds": ["cl3"],
    "sourceEntityId": "c7",
    "sourceEntityType": "conversation",
    "description": "8 out of 10 beta users rated onboarding 4+ out of 5. Sample size too small for statistical significance."
  },
  {
    "id": "e7",
    "title": "Competitor onboarding analysis",
    "source": "James Wilson",
    "sourceType": "document",
    "strength": "weak",
    "date": "2026-03-10T09:00:00Z",
    "url": null,
    "claimIds": ["cl3"],
    "sourceEntityId": "co2",
    "sourceEntityType": "communication",
    "description": "Comparison of 5 competitor onboarding flows. Our flow has fewer steps but competitors have higher completion rates."
  },
  {
    "id": "e8",
    "title": "CI/CD pipeline coverage report",
    "source": "GitHub Actions",
    "sourceType": "metric",
    "strength": "strong",
    "date": "2026-03-15T16:30:00Z",
    "url": null,
    "claimIds": ["cl4"],
    "sourceEntityId": "c4",
    "sourceEntityType": "conversation",
    "description": "Pipeline covers dev, staging, and production environments. All deployment steps automated with rollback capability."
  },
  {
    "id": "e9",
    "title": "Cross-browser test results",
    "source": "BrowserStack",
    "sourceType": "metric",
    "strength": "moderate",
    "date": "2026-04-03T14:00:00Z",
    "url": null,
    "claimIds": ["cl5"],
    "sourceEntityId": "co4",
    "sourceEntityType": "communication",
    "description": "Tested on Chrome, Firefox, Safari desktop. Mobile testing limited to iOS Safari and Chrome Android. 2 layout issues found on small screens."
  },
  {
    "id": "e10",
    "title": "Auth provider SLA document",
    "source": "Contract Documents",
    "sourceType": "document",
    "strength": "strong",
    "date": "2026-02-15T10:00:00Z",
    "url": null,
    "claimIds": ["cl6"],
    "sourceEntityId": null,
    "sourceEntityType": null,
    "description": "SLA guarantees 99.9% uptime. Actual March uptime was 99.7% due to incidents."
  }
]
